monacoreportwoo/__init__.py
monacoreportwoo/app/__init__.py
monacoreportwoo/app/app.py
monacoreportwoo/utils/__init__.py
monacoreportwoo/utils/exceptions.py
monacoreportwoo/utils/functions.py
monacoreportwoo/utils/utilitys.py
monacoreportwoo-1.7.dist-info/LICENSE
monacoreportwoo-1.7.dist-info/METADATA
monacoreportwoo-1.7.dist-info/WHEEL
monacoreportwoo-1.7.dist-info/entry_points.txt
monacoreportwoo-1.7.dist-info/top_level.txt
monacoreportwoo-1.7.dist-info/RECORD
