Metadata-Version: 2.1
Name: monacoreportwoo
Version: 1.7
Summary: Generate Monaco Racing report
Home-page: UNKNOWN
Author: Dihtiar Vadym
License: UNKNOWN
Platform: UNKNOWN
Requires-Python: >=3.8
License-File: LICENSE
Requires-Dist: texttable (==1.6.7)
Requires-Dist: pytest (==7.2.1)
